iothings/__init__.py
iothings/utils.py
iothings-0.2.0.dist-info/LICENSE
iothings-0.2.0.dist-info/METADATA
iothings-0.2.0.dist-info/WHEEL
iothings-0.2.0.dist-info/top_level.txt
iothings-0.2.0.dist-info/RECORD
