Metadata-Version: 2.2
Name: iothings
Version: 0.2.0
Summary: A Python library with useful I/O utilities.
Author-email: Jeroen Bertels <jeroen.bertels@gmail.com>
Project-URL: Homepage, https://github.com/JeroenBertels/iothings
Classifier: Programming Language :: Python :: 3
Classifier: License :: OSI Approved :: Apache Software License
Classifier: Operating System :: OS Independent
Requires-Python: >=3.8
License-File: LICENSE
